setup.py
NEB.egg-info/PKG-INFO
NEB.egg-info/SOURCES.txt
NEB.egg-info/dependency_links.txt
NEB.egg-info/top_level.txt
NEB.egg-info/zip-safe
neb/__init__.py