Metadata-Version: 1.0
Name: NEB
Version: 0.0.1
Summary: Namespace package for NEB projects.
Home-page: http://github.com/neb
Author: Paul J. Davis
Author-email: davisp@neb.com
License: MIT
Download-URL: http://github.com/neb/neb.git
Platform: UNKNOWN
Classifier: Development Status :: 3 - Alpha
Classifier: Intended Audience :: Developers
Classifier: Intended Audience :: Science/Research
Classifier: License :: OSI Approved :: MIT License
Classifier: Natural Language :: English
Classifier: Operating System :: OS Independent
Classifier: Programming Language :: Python
Classifier: Topic :: Scientific/Engineering :: Bio-Informatics
Classifier: Topic :: Software Development :: Libraries :: Python Modules
